zip2pdf/__init__.py
zip2pdf/main.py
zip2pdf-0.0.3.dist-info/METADATA
zip2pdf-0.0.3.dist-info/WHEEL
zip2pdf-0.0.3.dist-info/entry_points.txt
zip2pdf-0.0.3.dist-info/top_level.txt
zip2pdf-0.0.3.dist-info/RECORD
