Metadata-Version: 2.1
Name: zip2pdf
Version: 0.0.3
Requires-Dist: img2pdf
